cdk_dynamo_table_viewer/__init__.py
cdk_dynamo_table_viewer/py.typed
cdk_dynamo_table_viewer/_jsii/__init__.py
cdk_dynamo_table_viewer/_jsii/cdk-dynamo-table-viewer@3.1.2.jsii.tgz
cdk_dynamo_table_viewer-3.1.2.dist-info/METADATA
cdk_dynamo_table_viewer-3.1.2.dist-info/WHEEL
cdk_dynamo_table_viewer-3.1.2.dist-info/top_level.txt
cdk_dynamo_table_viewer-3.1.2.dist-info/RECORD
