Metadata-Version: 2.1
Name: cdk-dynamo-table-viewer
Version: 3.1.2
Summary: cdk-dynamo-table-viewer
Home-page: https://github.com/eladb/cdk-dynamo-table-viewer.git
Author: Elad Ben-Israel<elad.benisrael@gmail.com>
License: Apache-2.0
Project-URL: Source, https://github.com/eladb/cdk-dynamo-table-viewer.git
Platform: UNKNOWN
Classifier: Intended Audience :: Developers
Classifier: Operating System :: OS Independent
Classifier: Programming Language :: JavaScript
Classifier: Programming Language :: Python :: 3 :: Only
Classifier: Programming Language :: Python :: 3.6
Classifier: Programming Language :: Python :: 3.7
Classifier: Programming Language :: Python :: 3.8
Classifier: Typing :: Typed
Classifier: Development Status :: 4 - Beta
Classifier: License :: OSI Approved
Requires-Python: >=3.6
Requires-Dist: jsii (~=0.21.1)
Requires-Dist: publication (>=0.0.3)
Requires-Dist: aws-cdk.aws-apigateway (<2.0.0,>=1.20.0)
Requires-Dist: aws-cdk.aws-dynamodb (<2.0.0,>=1.20.0)
Requires-Dist: aws-cdk.aws-lambda (<2.0.0,>=1.20.0)
Requires-Dist: aws-cdk.core (<2.0.0,>=1.20.0)
